lcszh/__init__.py
lcszh/hit_stopwords.py
lcszh/utils.py
lcszh/word_cloud_diagram.py
lcszh-0.2.0.dist-info/METADATA
lcszh-0.2.0.dist-info/WHEEL
lcszh-0.2.0.dist-info/top_level.txt
lcszh-0.2.0.dist-info/RECORD
