Metadata-Version: 2.1
Name: lcszh
Version: 0.2.0
Summary: utils for lcszhlcy
Author: yyszh
Author-email: yyszhyyy@163.com
License: Apache License 2.0
Requires-Dist: xlrd (==1.2.0)
Requires-Dist: numpy
Requires-Dist: tqdm
Requires-Dist: python-docx
Requires-Dist: configparser
Requires-Dist: jieba
Requires-Dist: matplotlib
Requires-Dist: wordcloud
Requires-Dist: xlsxwriter (==3.0.1)
